<?xml version="1.0" encoding="utf-8" ?>
<resources>
 <resource key="page_title">Your Active Tasks - Field Work Manager</resource>
   <!-- Labels -->

  <resource key="active_task_header">View Task Status</resource>
  <resource key="active_task_map_header">View Task Map</resource>
  <resource key="active_task_forms_header">View Task Forms</resource>
  <resource key="active_task_comm_header">Discussions</resource>
  
  <resource key="message_success_startCommWith">Added to communication successfully</resource>
  <resource key="message_error_startCommWith">Failed to start communication</resource>
  <resource key="message_success_postNote">Note saved successfully</resource>
  <resource key="message_error_postNote">Failed to save Note</resource>
  <resource key="message_success_getNotes">Notes for this task populated</resource>
  <resource key="message_error_getNotes">No Note available yet.</resource>
  <resource key="message_success_sendMessage">Message was sent</resource>
  <resource key="message_error_sendMessage">Failed to send the message.</resource>

  <resource key="task_tab_info">Task Status</resource>
  <resource key="task_tab_map">Map</resource>
  <resource key="task_tab_forms">Forms</resource>
  <resource key="task_tab_comm">Communications</resource>
  
  <resource key="h4_taskstatus_leftcol">Task Progress</resource>
  <resource key="h4_taskstatus_instruction_label">Instructions</resource>
  <resource key="h4_taskstatus_notes_label">Notes</resource>
  <resource key="h4_taskstatus_noteshistory">Notes for this Task</resource>
  <resource key="h4_taskforms_leftcol">Completed Forms</resource>
  <resource key="h4_taskforms_rightcol">Forms used for this task</resource>
  <resource key="h4_taskcomm_leftcol">Discussion Thread</resource>
  <resource key="h4_taskcomm_rightcol">Who and What</resource>
  <resource key="h4_taskcomm_services">Service Providers</resource>
  <resource key="h4_taskcomm_technicians">Technicians</resource>
  
  <resource key="activetask_button_sendmsg">Send</resource>
  <resource key="activetask_button_attach">Attach File</resource>
  <resource key="btn_to_pm_list">Start discussion</resource>
  <resource key="btn_to_project_list">Unselect</resource>
  <resource key="at_status_savenote">Save</resource>
  <resource key="at_status_reloadnotes">Refresh</resource>
  
  <resource key="taskstatus_deadline_label">Task Deadline</resource>
  <resource key="taskstatus_daysremaining_label">Days Remaining</resource>
  <resource key="taskstatus_percentcomplete_label">Percent Complete</resource>
  <resource key="taskstatus_recurrence_label">Recurrence</resource>
  <resource key="taskstatus_manualtrigger_label">Manual Trigger</resource>
  <resource key="taskstatus_externaltrigger_label">External Trigger</resource>
</resources>